odoo/addons/business_requirement_sale_timesheet/README.rst
odoo/addons/business_requirement_sale_timesheet/__init__.py
odoo/addons/business_requirement_sale_timesheet/__manifest__.py
odoo/addons/business_requirement_sale_timesheet/i18n/business_requirement_sale_timesheet.pot
odoo/addons/business_requirement_sale_timesheet/i18n/fr.po
odoo/addons/business_requirement_sale_timesheet/i18n/pt_BR.po
odoo/addons/business_requirement_sale_timesheet/i18n/sl.po
odoo/addons/business_requirement_sale_timesheet/models/__init__.py
odoo/addons/business_requirement_sale_timesheet/models/project_task.py
odoo/addons/business_requirement_sale_timesheet/readme/CONTRIBUTORS.rst
odoo/addons/business_requirement_sale_timesheet/readme/CREDITS.rst
odoo/addons/business_requirement_sale_timesheet/readme/DESCRIPTION.rst
odoo/addons/business_requirement_sale_timesheet/readme/USAGE.rst
odoo/addons/business_requirement_sale_timesheet/static/description/icon.png
odoo/addons/business_requirement_sale_timesheet/static/description/index.html
odoo/addons/business_requirement_sale_timesheet/tests/__init__.py
odoo/addons/business_requirement_sale_timesheet/tests/test_business_requirement_sale_timesheet.py
odoo/addons/business_requirement_sale_timesheet/views/project_task.xml
odoo12_addon_business_requirement_sale_timesheet-12.0.1.0.0.99.dev9.dist-info/METADATA
odoo12_addon_business_requirement_sale_timesheet-12.0.1.0.0.99.dev9.dist-info/WHEEL
odoo12_addon_business_requirement_sale_timesheet-12.0.1.0.0.99.dev9.dist-info/top_level.txt
odoo12_addon_business_requirement_sale_timesheet-12.0.1.0.0.99.dev9.dist-info/RECORD
